qqai/__init__.py
qqai/classes.py
qqai/qqai.py
qqai/aai/__init__.py
qqai/aai/audio.py
qqai/aai/tts.py
qqai/nlp/__init__.py
qqai/nlp/text.py
qqai/nlp/translate.py
qqai/vision/__init__.py
qqai/vision/face.py
qqai/vision/ocr.py
qqai/vision/picture.py
qqai/vision/ptu.py
qqai-0.2.1.dist-info/LICENSE
qqai-0.2.1.dist-info/METADATA
qqai-0.2.1.dist-info/WHEEL
qqai-0.2.1.dist-info/top_level.txt
qqai-0.2.1.dist-info/RECORD
