Metadata-Version: 2.1
Name: qqai
Version: 0.2.1
Summary: Easy use of apis for Tencent AI
Home-page: https://github.com/clumsyme/qqai
Author: Li Yan
Author-email: me@imliyan.com
License: MIT
Platform: UNKNOWN
Classifier: License :: OSI Approved :: MIT License
Classifier: Programming Language :: Python
Classifier: Programming Language :: Python :: 3.6
Classifier: Programming Language :: Python :: Implementation :: CPython
Classifier: Programming Language :: Python :: Implementation :: PyPy
Requires-Python: >=3.6.0
Requires-Dist: requests
